{
  "parent": "projecte:alchemical_coal",
  "criteria": {
    "alchemical_coal_block": {
      "conditions": {
        "items": [
          {
            "items": [
              "projecte:alchemical_coal_block"
            ]
          }
        ]
      },
      "trigger": "minecraft:inventory_changed"
    }
  },
  "display": {
    "announce_to_chat": true,
    "description": {
      "translate": "advancements.projecte.alchemical_coal_block.description"
    },
    "frame": "task",
    "hidden": false,
    "icon": {
      "item": "projecte:alchemical_coal_block"
    },
    "show_toast": true,
    "title": {
      "translate": "advancements.projecte.alchemical_coal_block"
    }
  },
  "requirements": [
    [
      "alchemical_coal_block"
    ]
  ],
  "sends_telemetry_event": true
}
